crowdnalysis/__init__.py
crowdnalysis/_version.py
crowdnalysis/agreement.py
crowdnalysis/analysis.py
crowdnalysis/consensus.py
crowdnalysis/data.py
crowdnalysis/dawid_skene.py
crowdnalysis/factory.py
crowdnalysis/measures.py
crowdnalysis/problems.py
crowdnalysis/simple.py
crowdnalysis/visualization.py
crowdnalysis/cmdstan/__init__.py
crowdnalysis/cmdstan/dawid_skene.py
crowdnalysis/cmdstan/multinomial.py
crowdnalysis/cmdstan/cmdstan/DS.consensus.stan
crowdnalysis/cmdstan/cmdstan/DS.fit.stan
crowdnalysis/cmdstan/cmdstan/DS.fit_and_consensus.stan
crowdnalysis/cmdstan/cmdstan/DSEta.fit_and_consensus.stan
crowdnalysis/cmdstan/cmdstan/DSEtaH.fit.stan
crowdnalysis/cmdstan/cmdstan/DSEtaH.fit_and_consensus.stan
crowdnalysis/cmdstan/cmdstan/Multinomial.consensus.stan
crowdnalysis/cmdstan/cmdstan/Multinomial.fit.stan
crowdnalysis/cmdstan/cmdstan/Multinomial.fit_and_consensus.stan
crowdnalysis/cmdstan/cmdstan/Multinomial.sample_annotations.stan
crowdnalysis/cmdstan/cmdstan/Multinomial.sample_tasks.stan
crowdnalysis/cmdstan/cmdstan/MultinomialEta.fit.stan
crowdnalysis/cmdstan/cmdstan/MultinomialEta.fit_and_consensus.stan
crowdnalysis/cmdstan/cmdstan/dirichlet_alternative.stan
crowdnalysis/cmdstan/cmdstan/ds.stan
crowdnalysis/cmdstan/cmdstan/functions.stan
crowdnalysis/cmdstan/cmdstan/multinomial.stan
crowdnalysis/test/__init__.py
crowdnalysis/test/common.py
crowdnalysis/test/conftest.py
crowdnalysis/test/test_agreement.py
crowdnalysis/test/test_analysis.py
crowdnalysis/test/test_cmdstan_dawid_skene.py
crowdnalysis/test/test_cmdstan_multinomial.py
crowdnalysis/test/test_data.py
crowdnalysis/test/test_dawid_skene.py
crowdnalysis/test/test_factory.py
crowdnalysis/test/test_measures.py
crowdnalysis/test/test_problems.py
crowdnalysis/test/test_simple.py
crowdnalysis/test/test_version.py
crowdnalysis/test/test_visualization.py
crowdnalysis-1.1.2.dist-info/LICENSE
crowdnalysis-1.1.2.dist-info/METADATA
crowdnalysis-1.1.2.dist-info/WHEEL
crowdnalysis-1.1.2.dist-info/top_level.txt
crowdnalysis-1.1.2.dist-info/RECORD
