Metadata-Version: 2.1
Name: crowdnalysis
Version: 1.1.2
Summary: Library to help analyze crowdsourcing results
Home-page: https://github.com/Crowd4SDG/crowdnalysis
Author: IIIA-CSIC
Project-URL: Tutorial, https://github.com/Crowd4SDG/crowdnalysis/blob/master/nb/tutorial.ipynb
Project-URL: Issue Tracker, https://github.com/Crowd4SDG/crowdnalysis/issues
Keywords: citizen-science crowdsourcing annotation-aggregation annotator-model prospective-analysis
Classifier: License :: OSI Approved :: GNU Affero General Public License v3 or later (AGPLv3+)
Classifier: Operating System :: OS Independent
Classifier: Intended Audience :: Science/Research
Classifier: Topic :: Scientific/Engineering :: Information Analysis
Classifier: Programming Language :: Python :: 3
Classifier: Programming Language :: Python :: 3.7
Classifier: Programming Language :: Python :: 3.8
Classifier: Programming Language :: Python :: 3.9
Requires-Python: >=3.7
License-File: LICENSE
Requires-Dist: pandas
Requires-Dist: jupyter
Requires-Dist: matplotlib
Requires-Dist: seaborn
Requires-Dist: statsmodels
Requires-Dist: dominate
Requires-Dist: cmdstanpy
Requires-Dist: pytest
Requires-Dist: numpyencoder
Requires-Dist: flake8
Requires-Dist: coverage
Requires-Dist: pytest-cov
